README.txt
setup.cfg
setup.py
fbadSpace.egg-info/PKG-INFO
fbadSpace.egg-info/SOURCES.txt
fbadSpace.egg-info/dependency_links.txt
fbadSpace.egg-info/top_level.txt
fbadspace/__init__.py
fbadspace/utils.py
fbadspace/adobjects/__init__.py
fbadspace/adobjects/adaccountwrap.py
fbadspace/adobjects/businesswrap.py
fbadspace/adobjects/exportadreport.py