Metadata-Version: 1.0
Name: fbadSpace
Version: 0.4.1
Summary: facebookads wrapper
Home-page: UNKNOWN
Author: Alberto Egido
Author-email: alberto.egido@hotmail.com
License: UNKNOWN
Platform: UNKNOWN
